sudoku_manager/__init__.py
sudoku_manager/area.py
sudoku_manager/cell.py
sudoku_manager/sudoku.py
sudoku_manager-1.0.6.dist-info/LICENCE.txt
sudoku_manager-1.0.6.dist-info/METADATA
sudoku_manager-1.0.6.dist-info/WHEEL
sudoku_manager-1.0.6.dist-info/top_level.txt
sudoku_manager-1.0.6.dist-info/RECORD
