Metadata-Version: 2.1
Name: sudoku-manager
Version: 1.0.6
Summary: Package to easily generate and/or solve any 9x9 sudoku grid
Home-page: https://github.com/Jordan-Kowal/sudoku_manager
Author: Jordan Kowal
Author-email: kowaljordan@gmail.com
License: MIT
Download-URL: https://github.com/Jordan-Kowal/sudoku_manager/archive/v1.0.6.tar.gz
Keywords: sudoku,generator,solver,easy,generate,solve
Platform: UNKNOWN
Classifier: Development Status :: 5 - Production/Stable
Classifier: Intended Audience :: Developers
Classifier: Topic :: Software Development :: Build Tools
Classifier: License :: OSI Approved :: MIT License
Classifier: Programming Language :: Python :: 3
